aocutil/__init__.py
aocutil/aoc.py
aocutil-0.1.0.dist-info/METADATA
aocutil-0.1.0.dist-info/WHEEL
aocutil-0.1.0.dist-info/RECORD
