Metadata-Version: 2.1
Name: aocutil
Version: 0.1.0
Summary: Utility library for Advent of Code (https://adventofcode.com)
Author: Armin Friedl
Author-email: dev@friedl.net
Requires-Python: >=3.9,<3.10
Classifier: Programming Language :: Python :: 3
Classifier: Programming Language :: Python :: 3.9
Requires-Dist: pyquery (>=1.4.3,<2.0.0)
Requires-Dist: requests (>=2.28.1,<3.0.0)
